image_source_server/__init__.py
image_source_server-1.0.1.dist-info/LICENSE
image_source_server-1.0.1.dist-info/METADATA
image_source_server-1.0.1.dist-info/WHEEL
image_source_server-1.0.1.dist-info/top_level.txt
image_source_server-1.0.1.dist-info/RECORD
