Metadata-Version: 2.1
Name: image-source-server
Version: 1.0.1
Summary: Server for the Image Source app (available on Expo). Image Source helps send images, get predictions on images and train image models.
Home-page: https://github.com/prasannals/image_source_server
Author: Prasanna Lakkur Subramanyam
Author-email: prasanna.lakkur@gmail.com
License: UNKNOWN
Platform: UNKNOWN
Classifier: Programming Language :: Python :: 3
Classifier: License :: OSI Approved :: MIT License
Classifier: Operating System :: OS Independent
